ipl_stats/2008_2021_data_matches.csv
ipl_stats/2008_2021_updated_ball.csv
ipl_stats/__init__.py
ipl_stats/app.py
ipl_stats/deliveries.csv
ipl_stats/matches.csv
ipl_stats/modules.py
ipl_stats/runserver.py
ipl_stats/teammodules.py
ipl_stats/teamutils.py
ipl_stats/utils.py
ipl_stats-0.1.2.2.dist-info/entry_points.txt
ipl_stats-0.1.2.2.dist-info/LICENSE
ipl_stats-0.1.2.2.dist-info/WHEEL
ipl_stats-0.1.2.2.dist-info/METADATA
ipl_stats-0.1.2.2.dist-info/RECORD
